semaphore/__init__.py
semaphore/address.py
semaphore/attachment.py
semaphore/bot.py
semaphore/chat_context.py
semaphore/data_message.py
semaphore/exceptions.py
semaphore/group.py
semaphore/groupV2.py
semaphore/job.py
semaphore/job_queue.py
semaphore/link_preview.py
semaphore/mention.py
semaphore/message.py
semaphore/message_receiver.py
semaphore/message_sender.py
semaphore/meta.py
semaphore/profile.py
semaphore/queue.py
semaphore/reply.py
semaphore/socket.py
semaphore/sticker.py
semaphore/sticker_pack.py
semaphore_bot-0.17.0.dist-info/LICENSE.txt
semaphore_bot-0.17.0.dist-info/METADATA
semaphore_bot-0.17.0.dist-info/WHEEL
semaphore_bot-0.17.0.dist-info/top_level.txt
semaphore_bot-0.17.0.dist-info/RECORD
