Metadata-Version: 2.1
Name: semaphore-bot
Version: 0.17.0
Summary: Semaphore: A simple (rule-based) bot library for Signal Private Messenger.
Home-page: https://github.com/lwesterhof/semaphore
Author: Lazlo Westerhof
Author-email: semaphore@lazlo.me
License: AGPLv3+
Project-URL: Bug Reports, https://github.com/lwesterhof/semaphore/issues
Project-URL: Source, https://github.com/lwesterhof/semaphore
Classifier: Development Status :: 4 - Beta
Classifier: Intended Audience :: Developers
Classifier: License :: OSI Approved :: GNU Affero General Public License v3 or later (AGPLv3+)
Classifier: Operating System :: OS Independent
Classifier: Topic :: Software Development :: Libraries :: Python Modules
Classifier: Topic :: Communications :: Chat
Classifier: Topic :: Internet
Classifier: Programming Language :: Python
Classifier: Programming Language :: Python :: 3
Classifier: Programming Language :: Python :: 3.7
Classifier: Programming Language :: Python :: 3.8
Classifier: Programming Language :: Python :: 3.9
Classifier: Programming Language :: Python :: 3.10
Classifier: Programming Language :: Python :: 3.11
Requires-Python: >=3.7
License-File: LICENSE.txt
Requires-Dist: anyio (<=3.6.2,>=3.5.0)
Requires-Dist: attrs (<=22.2.0,>=21.2.0)
Requires-Dist: python-dateutil (==2.8.2)
Provides-Extra: dev
Requires-Dist: darglint ; extra == 'dev'
Requires-Dist: flake8 ; extra == 'dev'
Requires-Dist: flake8-import-order ; extra == 'dev'
Requires-Dist: mypy ; extra == 'dev'
Requires-Dist: sphinx ; extra == 'dev'
Requires-Dist: sphinx-rtd-theme ; extra == 'dev'
Requires-Dist: types-python-dateutil ; extra == 'dev'
